clustering_algorithms/__init__.py
clustering_algorithms/c_means.py
clustering_algorithms/clustering_algorithm.py
clustering_algorithms/clustering_exception.py
clustering_algorithms/k_means.py
clustering_algorithms-0.5.0.dist-info/LICENSE.txt
clustering_algorithms-0.5.0.dist-info/METADATA
clustering_algorithms-0.5.0.dist-info/WHEEL
clustering_algorithms-0.5.0.dist-info/top_level.txt
clustering_algorithms-0.5.0.dist-info/RECORD
