Metadata-Version: 2.1
Name: clustering_algorithms
Version: 0.5.0
Summary: Clustering algorithms powered by Numpy
Author-email: Yan Georget <yan.georget@gmail.com>
License: MIT License
Project-URL: Homepage, https://github.com/yangeorget/clustering-algorithms
Project-URL: Issues, https://github.com/yangeorget/clustering-algorithms
Classifier: Programming Language :: Python :: 3
Classifier: Operating System :: OS Independent
Requires-Python: >=3.8
License-File: LICENSE.txt
Requires-Dist: numpy
